pydra/tasks/dcm2bids/__init__.py
pydra_dcm2bids-0.0.4.dist-info/METADATA
pydra_dcm2bids-0.0.4.dist-info/WHEEL
pydra_dcm2bids-0.0.4.dist-info/licenses/LICENSE
pydra_dcm2bids-0.0.4.dist-info/RECORD
