Metadata-Version: 2.1
Name: pydra-dcm2bids
Version: 0.0.4
Summary: Pydra tasks for dcm2bids
Project-URL: Documentation, https://aramis-lab.github.io/pydra-dcm2bids
Project-URL: Issues, https://github.com/aramis-lab/pydra-dcm2bids/issues
Project-URL: Source, https://github.com/aramis-lab/pydra-dcm2bids
Author-email: Ghislain Vaillant <ghislain.vaillant@icm-institute.org>
License-Expression: Apache-2.0
License-File: LICENSE
Keywords: bids,dicom,pydra
Classifier: Development Status :: 3 - Alpha
Classifier: Intended Audience :: Science/Research
Classifier: License :: OSI Approved :: Apache Software License
Classifier: Operating System :: OS Independent
Classifier: Programming Language :: Python :: 3
Classifier: Programming Language :: Python :: 3.7
Classifier: Programming Language :: Python :: 3.8
Classifier: Programming Language :: Python :: 3.9
Classifier: Programming Language :: Python :: 3.10
Classifier: Programming Language :: Python :: 3.11
Classifier: Topic :: Scientific/Engineering
Classifier: Topic :: Software Development :: Libraries
Requires-Python: >=3.7
Requires-Dist: attrs>=22.1
Requires-Dist: pydra>=0.21
Provides-Extra: all
Requires-Dist: dcm2bids<3,>=2.1; extra == 'all'
